giftpack/__init__.py
giftpack/commands/__init__.py
giftpack/commands/addgift.py
giftpack/commands/delgift.py
giftpack/commands/getgift.py
giftpack/commands/getgiftdst.py
giftpack/commands/getgiftid.py
giftpack/commands/getgiftsrc.py
giftpack/commands/listgifts.py
giftpack/events/__init__.py
giftpack/stars/__init__.py
giftpack/tables/__init__.py
giftpack/tables/xmasgift.py
giftpack/version.py
giftpack-1.0.2.dist-info/WHEEL
giftpack-1.0.2.dist-info/METADATA
giftpack-1.0.2.dist-info/RECORD
